<?xml version="1.0" encoding="UTF-8"?>

<mule xmlns:http="http://www.mulesoft.org/schema/mule/http" xmlns="http://www.mulesoft.org/schema/mule/core" xmlns:doc="http://www.mulesoft.org/schema/mule/documentation"
	xmlns:spring="http://www.springframework.org/schema/beans" 
	xmlns:xsi="http://www.w3.org/2001/XMLSchema-instance"
	xsi:schemaLocation="http://www.springframework.org/schema/beans http://www.springframework.org/schema/beans/spring-beans-current.xsd
http://www.mulesoft.org/schema/mule/core http://www.mulesoft.org/schema/mule/core/current/mule.xsd
http://www.mulesoft.org/schema/mule/http http://www.mulesoft.org/schema/mule/http/current/mule-http.xsd">
	<http:request-config name="HTTP_Request_Configuration" protocol="HTTPS" host="google.com" port="443" basePath="search" doc:name="HTTP Request Configuration"/>
	<flow name="http-requesterFlow">
		<until-successful maxRetries="2" millisBetweenRetries="6000" doc:name="Until Successful">
			<http:request config-ref="HTTP_Request_Configuration" path="/hello/{id}" method="GET" doc:name="HTTPS requester - google">
				<http:request-builder>
					<http:query-param paramName="name" value="rajhans"/>
					<http:uri-param paramName="id" value="123"/>
					<http:header headerName="findme" value="yes"/>
				</http:request-builder>
			</http:request>
		</until-successful>
	</flow>
</mule>
